moontool/__init__.py
moontool/__main__.py
moontool/moon.py
moontool-0.2.0.dist-info/LICENSE
moontool-0.2.0.dist-info/WHEEL
moontool-0.2.0.dist-info/METADATA
moontool-0.2.0.dist-info/RECORD
