Metadata-Version: 2.1
Name: moontool
Version: 0.2.0
Summary: John Walker's moontool.c astronomical calculation routines, extracted and ported to Python.
Keywords: moon
Author-email: Quentin Richert <noreply@richert.co>
Requires-Python: >= 3.12
Classifier: Programming Language :: Python :: 3
Classifier: Operating System :: OS Independent
Classifier: Intended Audience :: Developers
Project-URL: Homepage, https://github.com/qrichert/moontool
